<?xml version = '1.0' encoding = 'UTF-8'?>
<Relation class="oracle.dbtools.crest.model.design.logical.Relation" name="Redemption_Ticket_FK" directorySegmentName="seg_0" id="451E9735-7DE8-ED98-7575-5FE2FE45B618">
<createdBy>luthf</createdBy>
<createdTime>2023-03-13 12:07:06 UTC</createdTime>
<generatorID>8CDDCC7B-F621-FB0A-6884-03E65F760820</generatorID>
<ownerDesignName>Helpdesk</ownerDesignName>
<engineerTo>
<item key="B6E1D825-D21B-1AD8-4D64-C06CC7BB68FE" value="true"/>
</engineerTo>
<sourcePk>C0BE20A9-C734-DDB7-0CD1-4C747D640380</sourcePk>
<identifying>false</identifying>
<optionalSource>true</optionalSource>
<optionalTarget>false</optionalTarget>
<sourceCardinality>1</sourceCardinality>
<sourceEntity>45890054-DCD2-E8B2-B65E-AC1D7466121F</sourceEntity>
<targetCardinalityString>*</targetCardinalityString>
<targetEntity>4B1D560C-A863-113D-4A0D-0F5C0983CB7C</targetEntity>
<transferable>true</transferable>
<deleteRule>NO ACTION</deleteRule>
</Relation>