<?xml version = '1.0' encoding = 'UTF-8'?>
<Relation class="oracle.dbtools.crest.model.design.logical.Relation" name="Comment_Ticket_FK" directorySegmentName="seg_0" id="4B12245B-8437-696D-42FF-16130A28638A">
<createdBy>luthf</createdBy>
<createdTime>2023-03-13 12:07:06 UTC</createdTime>
<generatorID>A8A0689C-987A-4E2E-3579-BFE466892130</generatorID>
<ownerDesignName>Helpdesk</ownerDesignName>
<engineerTo>
<item key="B6E1D825-D21B-1AD8-4D64-C06CC7BB68FE" value="true"/>
</engineerTo>
<sourcePk>C0BE20A9-C734-DDB7-0CD1-4C747D640380</sourcePk>
<identifying>false</identifying>
<optionalSource>true</optionalSource>
<optionalTarget>false</optionalTarget>
<sourceCardinality>1</sourceCardinality>
<sourceEntity>45890054-DCD2-E8B2-B65E-AC1D7466121F</sourceEntity>
<targetCardinalityString>*</targetCardinalityString>
<targetEntity>0195B7E6-1B13-89D5-AB09-887139B9B710</targetEntity>
<transferable>true</transferable>
<deleteRule>NO ACTION</deleteRule>
</Relation>